ToolBox4Test/__init__.py
ToolBox4Test/invokeFuncTrack.py
ToolBox4Test/toolbox.bat
ToolBox4Test/toolbox.py
ToolBox4Test/BaseUtility/__init__.py
ToolBox4Test/BaseUtility/adbShell.py
ToolBox4Test/BaseUtility/dataDriver.py
ToolBox4Test/BaseUtility/iterToolkit.py
ToolBox4Test/BaseUtility/toolkit.py
ToolBox4Test/CaseData/__init__.py
ToolBox4Test/CaseData/generateXmind.py
ToolBox4Test/Common/Api_Template_Doc.yml
ToolBox4Test/Common/CMS_COMMON_ENUM.yml
ToolBox4Test/Common/CMS_Rules.yml
ToolBox4Test/Common/__init__.py
ToolBox4Test/Common/initConfig.py
ToolBox4Test/Common/initRequest.py
ToolBox4Test/Common/initRule.py
ToolBox4Test/Common/initUIEnv.py
ToolBox4Test-1.0.5.dist-info/LICENSE
ToolBox4Test-1.0.5.dist-info/METADATA
ToolBox4Test-1.0.5.dist-info/WHEEL
ToolBox4Test-1.0.5.dist-info/entry_points.txt
ToolBox4Test-1.0.5.dist-info/top_level.txt
ToolBox4Test-1.0.5.dist-info/RECORD
