Metadata-Version: 2.1
Name: ToolBox4Test
Version: 1.0.5
Summary: TestToolbox 测试工具箱
Home-page: https://gitlab.com/Gavinwhy/TestToolBox
Author: Gavin
Author-email: guowenwhy@foxmail.com
Classifier: Development Status :: 3 - Alpha
Classifier: Programming Language :: Python :: 3
Classifier: License :: OSI Approved :: MIT License
Classifier: Intended Audience :: Developers
Classifier: Operating System :: OS Independent
License-File: LICENSE
Requires-Dist: pyyaml (>=6.0)
Requires-Dist: jsonpath (>=0.82)
Requires-Dist: pytest (>=7.1.2)
Requires-Dist: selenium (>=4.9.0)
Requires-Dist: faker (>=13.3.2)
Requires-Dist: requests (>=2.29.0)
Requires-Dist: xmind (>=1.2.0)
Requires-Dist: loguru (>=0.5.3)
Requires-Dist: pymysql (>=1.0.2)
Requires-Dist: redis (>=3.5.3)
Requires-Dist: business-rules-enhanced (>=1.2.2)
